cliquest/__init__.py
cliquest/cli.cpython-312-darwin.so
cliquest-0.2.2.dist-info/LICENCE.txt
cliquest-0.2.2.dist-info/METADATA
cliquest-0.2.2.dist-info/WHEEL
cliquest-0.2.2.dist-info/top_level.txt
cliquest-0.2.2.dist-info/RECORD
