Metadata-Version: 2.1
Name: cliquest
Version: 0.2.2
Summary: A package for estimating CLI
Author: YN
Author-email: 
Classifier: Programming Language :: Python :: 3
Classifier: Programming Language :: Python :: Implementation :: CPython
Classifier: License :: OSI Approved :: MIT License
Classifier: Operating System :: OS Independent
Requires-Python: >=3.6
License-File: LICENCE.txt
